credit_semaphore/__init__.py
credit_semaphore/async_credit_semaphore.py
credit_semaphore/semutils.py
credit_semaphore/sync_credit_semaphore.py
credit_semaphore-0.1.3.dist-info/METADATA
credit_semaphore-0.1.3.dist-info/WHEEL
credit_semaphore-0.1.3.dist-info/top_level.txt
credit_semaphore-0.1.3.dist-info/RECORD
