Metadata-Version: 2.1
Name: credit-semaphore
Version: 0.1.3
Summary: Semaphore Based on Credits for Efficient Credit-Based API Throttling
Home-page: https://github.com/hangukquant/credit_semaphore
Download-URL: https://pypi.org/project/credit-semaphore/
Author: HangukQuant
Author-email: 
License-File: license.txt
Requires-Dist: opencv-python
